odoo9_addon_sale_discount_display_amount-9.0.1.0.1-py3.8-nspkg.pth
odoo_addons/sale_discount_display_amount/README.rst
odoo_addons/sale_discount_display_amount/__init__.py
odoo_addons/sale_discount_display_amount/__openerp__.py
odoo_addons/sale_discount_display_amount/hooks.py
odoo_addons/sale_discount_display_amount/i18n/es.po
odoo_addons/sale_discount_display_amount/i18n/es_ES.po
odoo_addons/sale_discount_display_amount/i18n/fr.po
odoo_addons/sale_discount_display_amount/i18n/sale_discount_display_amount.pot
odoo_addons/sale_discount_display_amount/models/__init__.py
odoo_addons/sale_discount_display_amount/models/sale_order.py
odoo_addons/sale_discount_display_amount/models/sale_order_line.py
odoo_addons/sale_discount_display_amount/readme/CONFIGURE.rst
odoo_addons/sale_discount_display_amount/readme/CONTRIBUTORS.rst
odoo_addons/sale_discount_display_amount/readme/DESCRIPTION.rst
odoo_addons/sale_discount_display_amount/readme/USAGE.rst
odoo_addons/sale_discount_display_amount/static/description/icon.png
odoo_addons/sale_discount_display_amount/static/description/index.html
odoo_addons/sale_discount_display_amount/tests/__init__.py
odoo_addons/sale_discount_display_amount/tests/test_discount_display_amount.py
odoo_addons/sale_discount_display_amount/views/sale_view.xml
odoo9_addon_sale_discount_display_amount-9.0.1.0.1.dist-info/METADATA
odoo9_addon_sale_discount_display_amount-9.0.1.0.1.dist-info/WHEEL
odoo9_addon_sale_discount_display_amount-9.0.1.0.1.dist-info/namespace_packages.txt
odoo9_addon_sale_discount_display_amount-9.0.1.0.1.dist-info/top_level.txt
odoo9_addon_sale_discount_display_amount-9.0.1.0.1.dist-info/RECORD
